Compiled from "ChatController.java"
public class com.artverse.api.ChatController {
  private final com.artverse.application.ChatService chatService;

  private final com.artverse.application.ApiKeyService apiKeyService;

  private final com.artverse.application.CurrentUserService currentUserService;

  public org.springframework.web.servlet.mvc.method.annotation.SseEmitter chat(java.lang.Long, java.util.Map<java.lang.String, java.lang.String>);
    Code:
       0: aload_2
       1: ldc           #1                  // String message
       3: invokeinterface #3,  2            // InterfaceMethod java/util/Map.get:(Ljava/lang/Object;)Ljava/lang/Object;
       8: checkcast     #9                  // class java/lang/String
      11: astore_3
      12: aload_0
      13: getfield      #11                 // Field chatService:Lcom/artverse/application/ChatService;
      16: aload_1
      17: aload_3
      18: invokevirtual #17                 // Method com/artverse/application/ChatService.saveUserMessage:(Ljava/lang/Long;Ljava/lang/String;)V
      21: aload_0
      22: getfield      #23                 // Field currentUserService:Lcom/artverse/application/CurrentUserService;
      25: invokevirtual #27                 // Method com/artverse/application/CurrentUserService.requireCurrentUser:()Lcom/artverse/domain/User;
      28: astore        4
      30: aload_0
      31: getfield      #33                 // Field apiKeyService:Lcom/artverse/application/ApiKeyService;
      34: aload         4
      36: aload_0
      37: aload_2
      38: invokevirtual #37                 // Method requestConfig:(Ljava/util/Map;)Lcom/artverse/application/UserProviderConfig;
      41: ldc           #41                 // String Please configure an LLM provider API key in Settings before using story chat.
      43: invokevirtual #43                 // Method com/artverse/application/ApiKeyService.requireProviderConfig:(Lcom/artverse/domain/User;Lcom/artverse/application/UserProviderConfig;Ljava/lang/String;)Lcom/artverse/application/UserProviderConfig;
      46: astore        5
      48: aload_0
      49: getfield      #11                 // Field chatService:Lcom/artverse/application/ChatService;
      52: aload_1
      53: aload         4
      55: invokevirtual #49                 // Method com/artverse/domain/User.getId:()Ljava/lang/Long;
      58: aload         5
      60: invokevirtual #55                 // Method com/artverse/application/ChatService.streamChat:(Ljava/lang/Long;Ljava/lang/Long;Lcom/artverse/application/UserProviderConfig;)Lorg/springframework/web/servlet/mvc/method/annotation/SseEmitter;
      63: areturn

  public java.util.List<com.artverse.domain.ChatMessage> getMessages(java.lang.Long);
    Code:
       0: aload_0
       1: getfield      #11                 // Field chatService:Lcom/artverse/application/ChatService;
       4: aload_1
       5: invokevirtual #59                 // Method com/artverse/application/ChatService.getMessages:(Ljava/lang/Long;)Ljava/util/List;
       8: areturn

  private com.artverse.application.UserProviderConfig requestConfig(java.util.Map<java.lang.String, java.lang.String>);
    Code:
       0: new           #63                 // class com/artverse/application/UserProviderConfig
       3: dup
       4: ldc           #65                 // String llm
       6: aload_1
       7: ldc           #67                 // String provider
       9: invokeinterface #3,  2            // InterfaceMethod java/util/Map.get:(Ljava/lang/Object;)Ljava/lang/Object;
      14: checkcast     #9                  // class java/lang/String
      17: aload_1
      18: ldc           #69                 // String label
      20: invokeinterface #3,  2            // InterfaceMethod java/util/Map.get:(Ljava/lang/Object;)Ljava/lang/Object;
      25: checkcast     #9                  // class java/lang/String
      28: aload_0
      29: aload_1
      30: ldc           #71                 // String api_key
      32: invokeinterface #3,  2            // InterfaceMethod java/util/Map.get:(Ljava/lang/Object;)Ljava/lang/Object;
      37: checkcast     #9                  // class java/lang/String
      40: aload_1
      41: ldc           #73                 // String apiKey
      43: invokeinterface #3,  2            // InterfaceMethod java/util/Map.get:(Ljava/lang/Object;)Ljava/lang/Object;
      48: checkcast     #9                  // class java/lang/String
      51: invokevirtual #75                 // Method firstNonBlank:(Ljava/lang/String;Ljava/lang/String;)Ljava/lang/String;
      54: aload_0
      55: aload_1
      56: ldc           #79                 // String base_url
      58: invokeinterface #3,  2            // InterfaceMethod java/util/Map.get:(Ljava/lang/Object;)Ljava/lang/Object;
      63: checkcast     #9                  // class java/lang/String
      66: aload_1
      67: ldc           #81                 // String baseUrl
      69: invokeinterface #3,  2            // InterfaceMethod java/util/Map.get:(Ljava/lang/Object;)Ljava/lang/Object;
      74: checkcast     #9                  // class java/lang/String
      77: invokevirtual #75                 // Method firstNonBlank:(Ljava/lang/String;Ljava/lang/String;)Ljava/lang/String;
      80: aload_1
      81: ldc           #83                 // String model
      83: invokeinterface #3,  2            // InterfaceMethod java/util/Map.get:(Ljava/lang/Object;)Ljava/lang/Object;
      88: checkcast     #9                  // class java/lang/String
      91: invokespecial #85                 // Method com/artverse/application/UserProviderConfig."<init>":(Ljava/lang/String;Ljava/lang/String;Ljava/lang/String;Ljava/lang/String;Ljava/lang/String;Ljava/lang/String;)V
      94: areturn

  private java.lang.String firstNonBlank(java.lang.String, java.lang.String);
    Code:
       0: aload_1
       1: ifnull        13
       4: aload_1
       5: invokevirtual #89                 // Method java/lang/String.isBlank:()Z
       8: ifne          13
      11: aload_1
      12: areturn
      13: aload_2
      14: areturn

  public com.artverse.api.ChatController(com.artverse.application.ChatService, com.artverse.application.ApiKeyService, com.artverse.application.CurrentUserService);
    Code:
       0: aload_0
       1: invokespecial #93                 // Method java/lang/Object."<init>":()V
       4: aload_0
       5: aload_1
       6: putfield      #11                 // Field chatService:Lcom/artverse/application/ChatService;
       9: aload_0
      10: aload_2
      11: putfield      #33                 // Field apiKeyService:Lcom/artverse/application/ApiKeyService;
      14: aload_0
      15: aload_3
      16: putfield      #23                 // Field currentUserService:Lcom/artverse/application/CurrentUserService;
      19: return
}
